sqllib/__init__.py
sqllib/BDB/__init__.py
sqllib/LiteDB/__init__.py
sqllib/LiteDB/v1.py
sqllib/MangoDB/__init__.py
sqllib/MangoDB/test_1.py
sqllib/SQLite/__init__.py
sqllib/SQLite/sqlite.py
sqllib/SQLite/test.py
sqllib/common/__init__.py
sqllib/common/base.py
sqllib/common/base_no_sql.py
sqllib/common/base_sql.py
sqllib/common/common.py
sqllib/common/connection_pool.py
sqllib/common/error.py
sqllib/mysql/__init__.py
sqllib/mysql/localhost_mysql.py
sqllib/mysql/mysql_.py
sqllib/mysql/mysqlbase.py
test/__init__.py
test/learn_unittest.py
test/test_nosql.py
test/test_sql.py
sqllib-0.2.6.3.dist-info/METADATA
sqllib-0.2.6.3.dist-info/WHEEL
sqllib-0.2.6.3.dist-info/top_level.txt
sqllib-0.2.6.3.dist-info/RECORD
