Metadata-Version: 2.1
Name: sqllib
Version: 0.2.6.3
Summary: 对MySQL, SQLite数据库进行接口集成.
Home-page: https://leecq.cn
Author: Lee CQ
Author-email: lee-cq@qq.com
License: Apache License 2.0
Keywords: mysql,API,SQLite,DB
Platform: any
Classifier: Development Status :: 5 - Production/Stable
Classifier: Intended Audience :: Developers
Classifier: License :: OSI Approved :: Apache Software License
Classifier: Programming Language :: Python
Classifier: Programming Language :: Python :: 3.6
Classifier: Programming Language :: Python :: 3.7
Classifier: Programming Language :: Python :: 3.8
Classifier: Programming Language :: Python :: 3.9
Classifier: Programming Language :: Python :: 3.10
Classifier: Topic :: Software Development
